{
  "metadata" : {
    "identifier" : "https://www.nettruyenio.com/truyen-tranh/con-gai-chong-that-de-thuong-396227",
    "title" : "Con Gái Chồng Thật Dễ Thương - Chapter 76",
    "subtitle" : null,
    "author" : null,
    "narrator" : null,
    "language" : "vi",
    "description" : null,
    "publisher" : "N/A",
    "subject" : null,
    "modified" : null,
    "published" : "2023-08-18",
    "duration" : 0,
    "abridged" : false,
    "conformsTo" : "https://readium.org/webpub-manifest/profiles/divina",
    "numberOfPages" : 106,
    "readingProgression" : "ttb",
    "belongsTo" : null,
    "presentation" : {
      "fit" : "width",
      "overflow" : "scrolled",
      "continuous" : true
    },
    "@type" : null,
    "schema:license" : null
  },
  "links" : [ {
    "rel" : "self",
    "href" : "https://raw.githubusercontent.com/thuvienonline40/book_storage_collection/main/comic_manifest.json",
    "type" : "application/divina+json"
  } ],
  "readingOrder" : [ {
    "href" : "https://raw.githubusercontent.com/quetcccd/comic_storage9/main/IMAGE/IMAGE_2ed46c0b408d7a8e54681c8ec9c6d249_40ba63ee960f580caa0f940d0903dd92_2ce1f16596ae9c701335e0b8c0188753.jpg",
    "type" : "image/jpeg",
    "bitrate" : 0,
    "duration" : 0,
    "title" : null,
    "properties" : null,
    "alternate" : [ {
      "href" : "https://i221.ntcdntempv3.com/data/images/39619/931927/001-2aae4a1.jpg?data=net",
      "type" : "image/jpeg",
      "bitrate" : 0,
      "duration" : 0,
      "title" : null,
      "properties" : null,
      "alternate" : null
    } ]
  }, {
    "href" : "https://raw.githubusercontent.com/quetcccd/comic_storage9/main/IMAGE/IMAGE_2ed46c0b408d7a8e54681c8ec9c6d249_40ba63ee960f580caa0f940d0903dd92_b1f40ecad72545b7908c0fdbd5ceb7d8.jpg",
    "type" : "image/jpeg",
    "bitrate" : 0,
    "duration" : 0,
    "title" : null,
    "properties" : null,
    "alternate" : [ {
      "href" : "https://i221.ntcdntempv3.com/data/images/39619/931927/002-2f9a673.jpg?data=net",
      "type" : "image/jpeg",
      "bitrate" : 0,
      "duration" : 0,
      "title" : null,
      "properties" : null,
      "alternate" : null
    } ]
  }, {
    "href" : "https://raw.githubusercontent.com/quetcccd/comic_storage9/main/IMAGE/IMAGE_2ed46c0b408d7a8e54681c8ec9c6d249_40ba63ee960f580caa0f940d0903dd92_62ec8b5003679d2391503b65baea02c2.jpg",
    "type" : "image/jpeg",
    "bitrate" : 0,
    "duration" : 0,
    "title" : null,
    "properties" : null,
    "alternate" : [ {
      "href" : "https://i221.ntcdntempv3.com/data/images/39619/931927/003-4385dd9.jpg?data=net",
      "type" : "image/jpeg",
      "bitrate" : 0,
      "duration" : 0,
      "title" : null,
      "properties" : null,
      "alternate" : null
    } ]
  }, {
    "href" : "https://raw.githubusercontent.com/quetcccd/comic_storage9/main/IMAGE/IMAGE_2ed46c0b408d7a8e54681c8ec9c6d249_40ba63ee960f580caa0f940d0903dd92_fd7ad5a6af3fc870943c068a0b4b15f0.jpg",
    "type" : "image/jpeg",
    "bitrate" : 0,
    "duration" : 0,
    "title" : null,
    "properties" : null,
    "alternate" : [ {
      "href" : "https://i221.ntcdntempv3.com/data/images/39619/931927/004-086995f.jpg?data=net",
      "type" : "image/jpeg",
      "bitrate" : 0,
      "duration" : 0,
      "title" : null,
      "properties" : null,
      "alternate" : null
    } ]
  }, {
    "href" : "https://raw.githubusercontent.com/quetcccd/comic_storage9/main/IMAGE/IMAGE_2ed46c0b408d7a8e54681c8ec9c6d249_40ba63ee960f580caa0f940d0903dd92_3d27ed63a6c79f2ee535c5a4cf367005.jpg",
    "type" : "image/jpeg",
    "bitrate" : 0,
    "duration" : 0,
    "title" : null,
    "properties" : null,
    "alternate" : [ {
      "href" : "https://i221.ntcdntempv3.com/data/images/39619/931927/005-86b05a7.jpg?data=net",
      "type" : "image/jpeg",
      "bitrate" : 0,
      "duration" : 0,
      "title" : null,
      "properties" : null,
      "alternate" : null
    } ]
  }, {
    "href" : "https://raw.githubusercontent.com/quetcccd/comic_storage9/main/IMAGE/IMAGE_2ed46c0b408d7a8e54681c8ec9c6d249_40ba63ee960f580caa0f940d0903dd92_dca8736e79fed55c22f5d40f06d99736.jpg",
    "type" : "image/jpeg",
    "bitrate" : 0,
    "duration" : 0,
    "title" : null,
    "properties" : null,
    "alternate" : [ {
      "href" : "https://i221.ntcdntempv3.com/data/images/39619/931927/006-4ff574f.jpg?data=net",
      "type" : "image/jpeg",
      "bitrate" : 0,
      "duration" : 0,
      "title" : null,
      "properties" : null,
      "alternate" : null
    } ]
  }, {
    "href" : "https://raw.githubusercontent.com/quetcccd/comic_storage9/main/IMAGE/IMAGE_2ed46c0b408d7a8e54681c8ec9c6d249_40ba63ee960f580caa0f940d0903dd92_65e855987c7357909aa667e3af2dd62b.jpg",
    "type" : "image/jpeg",
    "bitrate" : 0,
    "duration" : 0,
    "title" : null,
    "properties" : null,
    "alternate" : [ {
      "href" : "https://i221.ntcdntempv3.com/data/images/39619/931927/007-187e110.jpg?data=net",
      "type" : "image/jpeg",
      "bitrate" : 0,
      "duration" : 0,
      "title" : null,
      "properties" : null,
      "alternate" : null
    } ]
  }, {
    "href" : "https://raw.githubusercontent.com/quetcccd/comic_storage9/main/IMAGE/IMAGE_2ed46c0b408d7a8e54681c8ec9c6d249_40ba63ee960f580caa0f940d0903dd92_76276d06ec0308ebe2c65a42e872206d.jpg",
    "type" : "image/jpeg",
    "bitrate" : 0,
    "duration" : 0,
    "title" : null,
    "properties" : null,
    "alternate" : [ {
      "href" : "https://i221.ntcdntempv3.com/data/images/39619/931927/008-0b1d59f.jpg?data=net",
      "type" : "image/jpeg",
      "bitrate" : 0,
      "duration" : 0,
      "title" : null,
      "properties" : null,
      "alternate" : null
    } ]
  }, {
    "href" : "https://raw.githubusercontent.com/quetcccd/comic_storage9/main/IMAGE/IMAGE_2ed46c0b408d7a8e54681c8ec9c6d249_40ba63ee960f580caa0f940d0903dd92_7726b2085e201c5f4646fcd14f759960.jpg",
    "type" : "image/jpeg",
    "bitrate" : 0,
    "duration" : 0,
    "title" : null,
    "properties" : null,
    "alternate" : [ {
      "href" : "https://i221.ntcdntempv3.com/data/images/39619/931927/009-c985f8a.jpg?data=net",
      "type" : "image/jpeg",
      "bitrate" : 0,
      "duration" : 0,
      "title" : null,
      "properties" : null,
      "alternate" : null
    } ]
  }, {
    "href" : "https://raw.githubusercontent.com/quetcccd/comic_storage9/main/IMAGE/IMAGE_2ed46c0b408d7a8e54681c8ec9c6d249_40ba63ee960f580caa0f940d0903dd92_0d78cadf7c66fe9e6154e894975cfeb7.jpg",
    "type" : "image/jpeg",
    "bitrate" : 0,
    "duration" : 0,
    "title" : null,
    "properties" : null,
    "alternate" : [ {
      "href" : "https://i221.ntcdntempv3.com/data/images/39619/931927/010-e5ffcea.jpg?data=net",
      "type" : "image/jpeg",
      "bitrate" : 0,
      "duration" : 0,
      "title" : null,
      "properties" : null,
      "alternate" : null
    } ]
  }, {
    "href" : "https://raw.githubusercontent.com/quetcccd/comic_storage9/main/IMAGE/IMAGE_2ed46c0b408d7a8e54681c8ec9c6d249_40ba63ee960f580caa0f940d0903dd92_523fb2859d5133bba51f1f52347ce4e8.jpg",
    "type" : "image/jpeg",
    "bitrate" : 0,
    "duration" : 0,
    "title" : null,
    "properties" : null,
    "alternate" : [ {
      "href" : "https://i221.ntcdntempv3.com/data/images/39619/931927/011-fe299f6.jpg?data=net",
      "type" : "image/jpeg",
      "bitrate" : 0,
      "duration" : 0,
      "title" : null,
      "properties" : null,
      "alternate" : null
    } ]
  }, {
    "href" : "https://raw.githubusercontent.com/quetcccd/comic_storage9/main/IMAGE/IMAGE_2ed46c0b408d7a8e54681c8ec9c6d249_40ba63ee960f580caa0f940d0903dd92_2356c5be39f14ba8679591a263ed9dbe.jpg",
    "type" : "image/jpeg",
    "bitrate" : 0,
    "duration" : 0,
    "title" : null,
    "properties" : null,
    "alternate" : [ {
      "href" : "https://i221.ntcdntempv3.com/data/images/39619/931927/012-d173a77.jpg?data=net",
      "type" : "image/jpeg",
      "bitrate" : 0,
      "duration" : 0,
      "title" : null,
      "properties" : null,
      "alternate" : null
    } ]
  }, {
    "href" : "https://raw.githubusercontent.com/quetcccd/comic_storage9/main/IMAGE/IMAGE_2ed46c0b408d7a8e54681c8ec9c6d249_40ba63ee960f580caa0f940d0903dd92_06989c9e74d08bcf3fc08a6093d8095f.jpg",
    "type" : "image/jpeg",
    "bitrate" : 0,
    "duration" : 0,
    "title" : null,
    "properties" : null,
    "alternate" : [ {
      "href" : "https://i221.ntcdntempv3.com/data/images/39619/931927/013-2d95d98.jpg?data=net",
      "type" : "image/jpeg",
      "bitrate" : 0,
      "duration" : 0,
      "title" : null,
      "properties" : null,
      "alternate" : null
    } ]
  }, {
    "href" : "https://raw.githubusercontent.com/quetcccd/comic_storage9/main/IMAGE/IMAGE_2ed46c0b408d7a8e54681c8ec9c6d249_40ba63ee960f580caa0f940d0903dd92_aac0ca05d8ff08a0ae17d1697a58ff2a.jpg",
    "type" : "image/jpeg",
    "bitrate" : 0,
    "duration" : 0,
    "title" : null,
    "properties" : null,
    "alternate" : [ {
      "href" : "https://i221.ntcdntempv3.com/data/images/39619/931927/014-b77ad8c.jpg?data=net",
      "type" : "image/jpeg",
      "bitrate" : 0,
      "duration" : 0,
      "title" : null,
      "properties" : null,
      "alternate" : null
    } ]
  }, {
    "href" : "https://raw.githubusercontent.com/quetcccd/comic_storage9/main/IMAGE/IMAGE_2ed46c0b408d7a8e54681c8ec9c6d249_40ba63ee960f580caa0f940d0903dd92_29851c22bbff37d8a35f35bb27895f9c.jpg",
    "type" : "image/jpeg",
    "bitrate" : 0,
    "duration" : 0,
    "title" : null,
    "properties" : null,
    "alternate" : [ {
      "href" : "https://i221.ntcdntempv3.com/data/images/39619/931927/015-64eee73.jpg?data=net",
      "type" : "image/jpeg",
      "bitrate" : 0,
      "duration" : 0,
      "title" : null,
      "properties" : null,
      "alternate" : null
    } ]
  }, {
    "href" : "https://raw.githubusercontent.com/quetcccd/comic_storage9/main/IMAGE/IMAGE_2ed46c0b408d7a8e54681c8ec9c6d249_40ba63ee960f580caa0f940d0903dd92_53e4ba4af9bee597061aed1db8ee5790.jpg",
    "type" : "image/jpeg",
    "bitrate" : 0,
    "duration" : 0,
    "title" : null,
    "properties" : null,
    "alternate" : [ {
      "href" : "https://i221.ntcdntempv3.com/data/images/39619/931927/016-0b3d773.jpg?data=net",
      "type" : "image/jpeg",
      "bitrate" : 0,
      "duration" : 0,
      "title" : null,
      "properties" : null,
      "alternate" : null
    } ]
  }, {
    "href" : "https://raw.githubusercontent.com/quetcccd/comic_storage9/main/IMAGE/IMAGE_2ed46c0b408d7a8e54681c8ec9c6d249_40ba63ee960f580caa0f940d0903dd92_ca4b3cd715759424f0461f1448db7cee.jpg",
    "type" : "image/jpeg",
    "bitrate" : 0,
    "duration" : 0,
    "title" : null,
    "properties" : null,
    "alternate" : [ {
      "href" : "https://i221.ntcdntempv3.com/data/images/39619/931927/017-7d8e657.jpg?data=net",
      "type" : "image/jpeg",
      "bitrate" : 0,
      "duration" : 0,
      "title" : null,
      "properties" : null,
      "alternate" : null
    } ]
  }, {
    "href" : "https://raw.githubusercontent.com/quetcccd/comic_storage9/main/IMAGE/IMAGE_2ed46c0b408d7a8e54681c8ec9c6d249_40ba63ee960f580caa0f940d0903dd92_19e5e8db50fc43b5de93395d705da80d.jpg",
    "type" : "image/jpeg",
    "bitrate" : 0,
    "duration" : 0,
    "title" : null,
    "properties" : null,
    "alternate" : [ {
      "href" : "https://i221.ntcdntempv3.com/data/images/39619/931927/018-adc44ec.jpg?data=net",
      "type" : "image/jpeg",
      "bitrate" : 0,
      "duration" : 0,
      "title" : null,
      "properties" : null,
      "alternate" : null
    } ]
  }, {
    "href" : "https://raw.githubusercontent.com/quetcccd/comic_storage9/main/IMAGE/IMAGE_2ed46c0b408d7a8e54681c8ec9c6d249_40ba63ee960f580caa0f940d0903dd92_197ac77a489a729235d5a77d029572ae.jpg",
    "type" : "image/jpeg",
    "bitrate" : 0,
    "duration" : 0,
    "title" : null,
    "properties" : null,
    "alternate" : [ {
      "href" : "https://i221.ntcdntempv3.com/data/images/39619/931927/019-fea3fd2.jpg?data=net",
      "type" : "image/jpeg",
      "bitrate" : 0,
      "duration" : 0,
      "title" : null,
      "properties" : null,
      "alternate" : null
    } ]
  }, {
    "href" : "https://raw.githubusercontent.com/quetcccd/comic_storage9/main/IMAGE/IMAGE_2ed46c0b408d7a8e54681c8ec9c6d249_40ba63ee960f580caa0f940d0903dd92_b661406bbf002a6fb50afbed616a0207.jpg",
    "type" : "image/jpeg",
    "bitrate" : 0,
    "duration" : 0,
    "title" : null,
    "properties" : null,
    "alternate" : [ {
      "href" : "https://i221.ntcdntempv3.com/data/images/39619/931927/020-5df9ad6.jpg?data=net",
      "type" : "image/jpeg",
      "bitrate" : 0,
      "duration" : 0,
      "title" : null,
      "properties" : null,
      "alternate" : null
    } ]
  }, {
    "href" : "https://raw.githubusercontent.com/quetcccd/comic_storage9/main/IMAGE/IMAGE_2ed46c0b408d7a8e54681c8ec9c6d249_40ba63ee960f580caa0f940d0903dd92_deb60484b0b1e2cb00aecbad96bf9537.jpg",
    "type" : "image/jpeg",
    "bitrate" : 0,
    "duration" : 0,
    "title" : null,
    "properties" : null,
    "alternate" : [ {
      "href" : "https://i221.ntcdntempv3.com/data/images/39619/931927/021-c000f05.jpg?data=net",
      "type" : "image/jpeg",
      "bitrate" : 0,
      "duration" : 0,
      "title" : null,
      "properties" : null,
      "alternate" : null
    } ]
  }, {
    "href" : "https://raw.githubusercontent.com/quetcccd/comic_storage9/main/IMAGE/IMAGE_2ed46c0b408d7a8e54681c8ec9c6d249_40ba63ee960f580caa0f940d0903dd92_a58bf0cb06166dea7aa5165c81aa70b3.jpg",
    "type" : "image/jpeg",
    "bitrate" : 0,
    "duration" : 0,
    "title" : null,
    "properties" : null,
    "alternate" : [ {
      "href" : "https://i221.ntcdntempv3.com/data/images/39619/931927/022-99c4bf1.jpg?data=net",
      "type" : "image/jpeg",
      "bitrate" : 0,
      "duration" : 0,
      "title" : null,
      "properties" : null,
      "alternate" : null
    } ]
  }, {
    "href" : "https://raw.githubusercontent.com/quetcccd/comic_storage9/main/IMAGE/IMAGE_2ed46c0b408d7a8e54681c8ec9c6d249_40ba63ee960f580caa0f940d0903dd92_17e2691484921bcfe07d8b5931341024.jpg",
    "type" : "image/jpeg",
    "bitrate" : 0,
    "duration" : 0,
    "title" : null,
    "properties" : null,
    "alternate" : [ {
      "href" : "https://i221.ntcdntempv3.com/data/images/39619/931927/023-05d83f6.jpg?data=net",
      "type" : "image/jpeg",
      "bitrate" : 0,
      "duration" : 0,
      "title" : null,
      "properties" : null,
      "alternate" : null
    } ]
  }, {
    "href" : "https://raw.githubusercontent.com/quetcccd/comic_storage9/main/IMAGE/IMAGE_2ed46c0b408d7a8e54681c8ec9c6d249_40ba63ee960f580caa0f940d0903dd92_e3dfe229bae83965e970dabc52c1cf80.jpg",
    "type" : "image/jpeg",
    "bitrate" : 0,
    "duration" : 0,
    "title" : null,
    "properties" : null,
    "alternate" : [ {
      "href" : "https://i221.ntcdntempv3.com/data/images/39619/931927/024-5d0a2f6.jpg?data=net",
      "type" : "image/jpeg",
      "bitrate" : 0,
      "duration" : 0,
      "title" : null,
      "properties" : null,
      "alternate" : null
    } ]
  }, {
    "href" : "https://raw.githubusercontent.com/quetcccd/comic_storage9/main/IMAGE/IMAGE_2ed46c0b408d7a8e54681c8ec9c6d249_40ba63ee960f580caa0f940d0903dd92_438f5c82f1d78fa5d63d81353dbb226e.jpg",
    "type" : "image/jpeg",
    "bitrate" : 0,
    "duration" : 0,
    "title" : null,
    "properties" : null,
    "alternate" : [ {
      "href" : "https://i221.ntcdntempv3.com/data/images/39619/931927/025-3e6ab03.jpg?data=net",
      "type" : "image/jpeg",
      "bitrate" : 0,
      "duration" : 0,
      "title" : null,
      "properties" : null,
      "alternate" : null
    } ]
  }, {
    "href" : "https://raw.githubusercontent.com/quetcccd/comic_storage9/main/IMAGE/IMAGE_2ed46c0b408d7a8e54681c8ec9c6d249_40ba63ee960f580caa0f940d0903dd92_75477dfbc17233b95930ebd786ed27b9.jpg",
    "type" : "image/jpeg",
    "bitrate" : 0,
    "duration" : 0,
    "title" : null,
    "properties" : null,
    "alternate" : [ {
      "href" : "https://i221.ntcdntempv3.com/data/images/39619/931927/026-0b575ff.jpg?data=net",
      "type" : "image/jpeg",
      "bitrate" : 0,
      "duration" : 0,
      "title" : null,
      "properties" : null,
      "alternate" : null
    } ]
  }, {
    "href" : "https://raw.githubusercontent.com/quetcccd/comic_storage9/main/IMAGE/IMAGE_2ed46c0b408d7a8e54681c8ec9c6d249_40ba63ee960f580caa0f940d0903dd92_270738eaaa2a04f42d018a694b138822.jpg",
    "type" : "image/jpeg",
    "bitrate" : 0,
    "duration" : 0,
    "title" : null,
    "properties" : null,
    "alternate" : [ {
      "href" : "https://i221.ntcdntempv3.com/data/images/39619/931927/027-b0a2c00.jpg?data=net",
      "type" : "image/jpeg",
      "bitrate" : 0,
      "duration" : 0,
      "title" : null,
      "properties" : null,
      "alternate" : null
    } ]
  }, {
    "href" : "https://raw.githubusercontent.com/quetcccd/comic_storage9/main/IMAGE/IMAGE_2ed46c0b408d7a8e54681c8ec9c6d249_40ba63ee960f580caa0f940d0903dd92_bcdeaf233e75085b0af64bebc2236316.jpg",
    "type" : "image/jpeg",
    "bitrate" : 0,
    "duration" : 0,
    "title" : null,
    "properties" : null,
    "alternate" : [ {
      "href" : "https://i221.ntcdntempv3.com/data/images/39619/931927/028-fa4dc86.jpg?data=net",
      "type" : "image/jpeg",
      "bitrate" : 0,
      "duration" : 0,
      "title" : null,
      "properties" : null,
      "alternate" : null
    } ]
  }, {
    "href" : "https://raw.githubusercontent.com/quetcccd/comic_storage9/main/IMAGE/IMAGE_2ed46c0b408d7a8e54681c8ec9c6d249_40ba63ee960f580caa0f940d0903dd92_80cff454d4c347cc1601dd89d5d5a33e.jpg",
    "type" : "image/jpeg",
    "bitrate" : 0,
    "duration" : 0,
    "title" : null,
    "properties" : null,
    "alternate" : [ {
      "href" : "https://i221.ntcdntempv3.com/data/images/39619/931927/029-18738c2.jpg?data=net",
      "type" : "image/jpeg",
      "bitrate" : 0,
      "duration" : 0,
      "title" : null,
      "properties" : null,
      "alternate" : null
    } ]
  }, {
    "href" : "https://raw.githubusercontent.com/quetcccd/comic_storage9/main/IMAGE/IMAGE_2ed46c0b408d7a8e54681c8ec9c6d249_40ba63ee960f580caa0f940d0903dd92_204804cc0398c5e28f6c328dae597240.jpg",
    "type" : "image/jpeg",
    "bitrate" : 0,
    "duration" : 0,
    "title" : null,
    "properties" : null,
    "alternate" : [ {
      "href" : "https://i221.ntcdntempv3.com/data/images/39619/931927/030-4b3c402.jpg?data=net",
      "type" : "image/jpeg",
      "bitrate" : 0,
      "duration" : 0,
      "title" : null,
      "properties" : null,
      "alternate" : null
    } ]
  }, {
    "href" : "https://raw.githubusercontent.com/quetcccd/comic_storage9/main/IMAGE/IMAGE_2ed46c0b408d7a8e54681c8ec9c6d249_40ba63ee960f580caa0f940d0903dd92_dee08422c74987e2445cc0c825e50eea.jpg",
    "type" : "image/jpeg",
    "bitrate" : 0,
    "duration" : 0,
    "title" : null,
    "properties" : null,
    "alternate" : [ {
      "href" : "https://i221.ntcdntempv3.com/data/images/39619/931927/031-00802b1.jpg?data=net",
      "type" : "image/jpeg",
      "bitrate" : 0,
      "duration" : 0,
      "title" : null,
      "properties" : null,
      "alternate" : null
    } ]
  }, {
    "href" : "https://raw.githubusercontent.com/quetcccd/comic_storage9/main/IMAGE/IMAGE_2ed46c0b408d7a8e54681c8ec9c6d249_40ba63ee960f580caa0f940d0903dd92_0a13daf639ad20ec5bcac49f1538183b.jpg",
    "type" : "image/jpeg",
    "bitrate" : 0,
    "duration" : 0,
    "title" : null,
    "properties" : null,
    "alternate" : [ {
      "href" : "https://i221.ntcdntempv3.com/data/images/39619/931927/032-e5b8a34.jpg?data=net",
      "type" : "image/jpeg",
      "bitrate" : 0,
      "duration" : 0,
      "title" : null,
      "properties" : null,
      "alternate" : null
    } ]
  }, {
    "href" : "https://raw.githubusercontent.com/quetcccd/comic_storage9/main/IMAGE/IMAGE_2ed46c0b408d7a8e54681c8ec9c6d249_40ba63ee960f580caa0f940d0903dd92_095dbfa3af84986e058a4f3d304d8b56.jpg",
    "type" : "image/jpeg",
    "bitrate" : 0,
    "duration" : 0,
    "title" : null,
    "properties" : null,
    "alternate" : [ {
      "href" : "https://i221.ntcdntempv3.com/data/images/39619/931927/033-25ed627.jpg?data=net",
      "type" : "image/jpeg",
      "bitrate" : 0,
      "duration" : 0,
      "title" : null,
      "properties" : null,
      "alternate" : null
    } ]
  }, {
    "href" : "https://raw.githubusercontent.com/quetcccd/comic_storage9/main/IMAGE/IMAGE_2ed46c0b408d7a8e54681c8ec9c6d249_40ba63ee960f580caa0f940d0903dd92_7febaec0486e51c986ef6041546a4440.jpg",
    "type" : "image/jpeg",
    "bitrate" : 0,
    "duration" : 0,
    "title" : null,
    "properties" : null,
    "alternate" : [ {
      "href" : "https://i221.ntcdntempv3.com/data/images/39619/931927/034-891e756.jpg?data=net",
      "type" : "image/jpeg",
      "bitrate" : 0,
      "duration" : 0,
      "title" : null,
      "properties" : null,
      "alternate" : null
    } ]
  }, {
    "href" : "https://raw.githubusercontent.com/quetcccd/comic_storage9/main/IMAGE/IMAGE_2ed46c0b408d7a8e54681c8ec9c6d249_40ba63ee960f580caa0f940d0903dd92_68000bc66e215d1068828d0cf26ca952.jpg",
    "type" : "image/jpeg",
    "bitrate" : 0,
    "duration" : 0,
    "title" : null,
    "properties" : null,
    "alternate" : [ {
      "href" : "https://i221.ntcdntempv3.com/data/images/39619/931927/035-a83cd8d.jpg?data=net",
      "type" : "image/jpeg",
      "bitrate" : 0,
      "duration" : 0,
      "title" : null,
      "properties" : null,
      "alternate" : null
    } ]
  }, {
    "href" : "https://raw.githubusercontent.com/quetcccd/comic_storage9/main/IMAGE/IMAGE_2ed46c0b408d7a8e54681c8ec9c6d249_40ba63ee960f580caa0f940d0903dd92_73f52b5beb57f7b8158a946ed7c94916.jpg",
    "type" : "image/jpeg",
    "bitrate" : 0,
    "duration" : 0,
    "title" : null,
    "properties" : null,
    "alternate" : [ {
      "href" : "https://i221.ntcdntempv3.com/data/images/39619/931927/036-356fb27.jpg?data=net",
      "type" : "image/jpeg",
      "bitrate" : 0,
      "duration" : 0,
      "title" : null,
      "properties" : null,
      "alternate" : null
    } ]
  }, {
    "href" : "https://raw.githubusercontent.com/quetcccd/comic_storage9/main/IMAGE/IMAGE_2ed46c0b408d7a8e54681c8ec9c6d249_40ba63ee960f580caa0f940d0903dd92_1d3e22fcc8dbdc6eda7351ba56174c40.jpg",
    "type" : "image/jpeg",
    "bitrate" : 0,
    "duration" : 0,
    "title" : null,
    "properties" : null,
    "alternate" : [ {
      "href" : "https://i221.ntcdntempv3.com/data/images/39619/931927/037-3a30156.jpg?data=net",
      "type" : "image/jpeg",
      "bitrate" : 0,
      "duration" : 0,
      "title" : null,
      "properties" : null,
      "alternate" : null
    } ]
  }, {
    "href" : "https://raw.githubusercontent.com/quetcccd/comic_storage9/main/IMAGE/IMAGE_2ed46c0b408d7a8e54681c8ec9c6d249_40ba63ee960f580caa0f940d0903dd92_762b021ac280fce13627b78e5ac20b9b.jpg",
    "type" : "image/jpeg",
    "bitrate" : 0,
    "duration" : 0,
    "title" : null,
    "properties" : null,
    "alternate" : [ {
      "href" : "https://i221.ntcdntempv3.com/data/images/39619/931927/038-5ac97ed.jpg?data=net",
      "type" : "image/jpeg",
      "bitrate" : 0,
      "duration" : 0,
      "title" : null,
      "properties" : null,
      "alternate" : null
    } ]
  }, {
    "href" : "https://raw.githubusercontent.com/quetcccd/comic_storage9/main/IMAGE/IMAGE_2ed46c0b408d7a8e54681c8ec9c6d249_40ba63ee960f580caa0f940d0903dd92_a8efc8278b447174a21cafaac39c3f1c.jpg",
    "type" : "image/jpeg",
    "bitrate" : 0,
    "duration" : 0,
    "title" : null,
    "properties" : null,
    "alternate" : [ {
      "href" : "https://i221.ntcdntempv3.com/data/images/39619/931927/039-2984ca6.jpg?data=net",
      "type" : "image/jpeg",
      "bitrate" : 0,
      "duration" : 0,
      "title" : null,
      "properties" : null,
      "alternate" : null
    } ]
  }, {
    "href" : "https://raw.githubusercontent.com/quetcccd/comic_storage9/main/IMAGE/IMAGE_2ed46c0b408d7a8e54681c8ec9c6d249_40ba63ee960f580caa0f940d0903dd92_202cb665f5055578b3a9e65bd2329d7a.jpg",
    "type" : "image/jpeg",
    "bitrate" : 0,
    "duration" : 0,
    "title" : null,
    "properties" : null,
    "alternate" : [ {
      "href" : "https://i221.ntcdntempv3.com/data/images/39619/931927/040-c840c7a.jpg?data=net",
      "type" : "image/jpeg",
      "bitrate" : 0,
      "duration" : 0,
      "title" : null,
      "properties" : null,
      "alternate" : null
    } ]
  }, {
    "href" : "https://raw.githubusercontent.com/quetcccd/comic_storage9/main/IMAGE/IMAGE_2ed46c0b408d7a8e54681c8ec9c6d249_40ba63ee960f580caa0f940d0903dd92_4f5426c91e35a87d808227bbae7a77c1.jpg",
    "type" : "image/jpeg",
    "bitrate" : 0,
    "duration" : 0,
    "title" : null,
    "properties" : null,
    "alternate" : [ {
      "href" : "https://i221.ntcdntempv3.com/data/images/39619/931927/041-1752f42.jpg?data=net",
      "type" : "image/jpeg",
      "bitrate" : 0,
      "duration" : 0,
      "title" : null,
      "properties" : null,
      "alternate" : null
    } ]
  }, {
    "href" : "https://raw.githubusercontent.com/quetcccd/comic_storage9/main/IMAGE/IMAGE_2ed46c0b408d7a8e54681c8ec9c6d249_40ba63ee960f580caa0f940d0903dd92_89a939db0a6d306d4bab89fe30ae7f78.jpg",
    "type" : "image/jpeg",
    "bitrate" : 0,
    "duration" : 0,
    "title" : null,
    "properties" : null,
    "alternate" : [ {
      "href" : "https://i221.ntcdntempv3.com/data/images/39619/931927/042-7becb58.jpg?data=net",
      "type" : "image/jpeg",
      "bitrate" : 0,
      "duration" : 0,
      "title" : null,
      "properties" : null,
      "alternate" : null
    } ]
  }, {
    "href" : "https://raw.githubusercontent.com/quetcccd/comic_storage9/main/IMAGE/IMAGE_2ed46c0b408d7a8e54681c8ec9c6d249_40ba63ee960f580caa0f940d0903dd92_34f5eac792e876cd45a38351a547359d.jpg",
    "type" : "image/jpeg",
    "bitrate" : 0,
    "duration" : 0,
    "title" : null,
    "properties" : null,
    "alternate" : [ {
      "href" : "https://i221.ntcdntempv3.com/data/images/39619/931927/043-4970200.jpg?data=net",
      "type" : "image/jpeg",
      "bitrate" : 0,
      "duration" : 0,
      "title" : null,
      "properties" : null,
      "alternate" : null
    } ]
  }, {
    "href" : "https://raw.githubusercontent.com/quetcccd/comic_storage9/main/IMAGE/IMAGE_2ed46c0b408d7a8e54681c8ec9c6d249_40ba63ee960f580caa0f940d0903dd92_2e9c7d7ebc3c32e3cbe49a89b03d83ab.jpg",
    "type" : "image/jpeg",
    "bitrate" : 0,
    "duration" : 0,
    "title" : null,
    "properties" : null,
    "alternate" : [ {
      "href" : "https://i221.ntcdntempv3.com/data/images/39619/931927/044-2aae8a5.jpg?data=net",
      "type" : "image/jpeg",
      "bitrate" : 0,
      "duration" : 0,
      "title" : null,
      "properties" : null,
      "alternate" : null
    } ]
  }, {
    "href" : "https://raw.githubusercontent.com/quetcccd/comic_storage9/main/IMAGE/IMAGE_2ed46c0b408d7a8e54681c8ec9c6d249_40ba63ee960f580caa0f940d0903dd92_f3f1f32f36fe246b2f3399d8146d7433.jpg",
    "type" : "image/jpeg",
    "bitrate" : 0,
    "duration" : 0,
    "title" : null,
    "properties" : null,
    "alternate" : [ {
      "href" : "https://i221.ntcdntempv3.com/data/images/39619/931927/045-81a4281.jpg?data=net",
      "type" : "image/jpeg",
      "bitrate" : 0,
      "duration" : 0,
      "title" : null,
      "properties" : null,
      "alternate" : null
    } ]
  }, {
    "href" : "https://raw.githubusercontent.com/quetcccd/comic_storage9/main/IMAGE/IMAGE_2ed46c0b408d7a8e54681c8ec9c6d249_40ba63ee960f580caa0f940d0903dd92_b2b937378b86244f89dba4e54a377ef5.jpg",
    "type" : "image/jpeg",
    "bitrate" : 0,
    "duration" : 0,
    "title" : null,
    "properties" : null,
    "alternate" : [ {
      "href" : "https://i221.ntcdntempv3.com/data/images/39619/931927/046-33fe951.jpg?data=net",
      "type" : "image/jpeg",
      "bitrate" : 0,
      "duration" : 0,
      "title" : null,
      "properties" : null,
      "alternate" : null
    } ]
  }, {
    "href" : "https://raw.githubusercontent.com/quetcccd/comic_storage9/main/IMAGE/IMAGE_2ed46c0b408d7a8e54681c8ec9c6d249_40ba63ee960f580caa0f940d0903dd92_8a3d5af5c5524559fec368fa67606799.jpg",
    "type" : "image/jpeg",
    "bitrate" : 0,
    "duration" : 0,
    "title" : null,
    "properties" : null,
    "alternate" : [ {
      "href" : "https://i221.ntcdntempv3.com/data/images/39619/931927/047-ffb9350.jpg?data=net",
      "type" : "image/jpeg",
      "bitrate" : 0,
      "duration" : 0,
      "title" : null,
      "properties" : null,
      "alternate" : null
    } ]
  }, {
    "href" : "https://raw.githubusercontent.com/quetcccd/comic_storage9/main/IMAGE/IMAGE_2ed46c0b408d7a8e54681c8ec9c6d249_40ba63ee960f580caa0f940d0903dd92_d6be2f17e0edc22c6ad03f1b3416cd21.jpg",
    "type" : "image/jpeg",
    "bitrate" : 0,
    "duration" : 0,
    "title" : null,
    "properties" : null,
    "alternate" : [ {
      "href" : "https://i221.ntcdntempv3.com/data/images/39619/931927/048-04f7f3d.jpg?data=net",
      "type" : "image/jpeg",
      "bitrate" : 0,
      "duration" : 0,
      "title" : null,
      "properties" : null,
      "alternate" : null
    } ]
  }, {
    "href" : "https://raw.githubusercontent.com/quetcccd/comic_storage9/main/IMAGE/IMAGE_2ed46c0b408d7a8e54681c8ec9c6d249_40ba63ee960f580caa0f940d0903dd92_53e898a7715084553852ec824ba6dbbd.jpg",
    "type" : "image/jpeg",
    "bitrate" : 0,
    "duration" : 0,
    "title" : null,
    "properties" : null,
    "alternate" : [ {
      "href" : "https://i221.ntcdntempv3.com/data/images/39619/931927/049-ce1c960.jpg?data=net",
      "type" : "image/jpeg",
      "bitrate" : 0,
      "duration" : 0,
      "title" : null,
      "properties" : null,
      "alternate" : null
    } ]
  }, {
    "href" : "https://raw.githubusercontent.com/quetcccd/comic_storage9/main/IMAGE/IMAGE_2ed46c0b408d7a8e54681c8ec9c6d249_40ba63ee960f580caa0f940d0903dd92_3133eb5dc7f96f8051616e0f7efef39f.jpg",
    "type" : "image/jpeg",
    "bitrate" : 0,
    "duration" : 0,
    "title" : null,
    "properties" : null,
    "alternate" : [ {
      "href" : "https://i221.ntcdntempv3.com/data/images/39619/931927/050-86598dc.jpg?data=net",
      "type" : "image/jpeg",
      "bitrate" : 0,
      "duration" : 0,
      "title" : null,
      "properties" : null,
      "alternate" : null
    } ]
  }, {
    "href" : "https://raw.githubusercontent.com/quetcccd/comic_storage9/main/IMAGE/IMAGE_2ed46c0b408d7a8e54681c8ec9c6d249_40ba63ee960f580caa0f940d0903dd92_a44023fe143e8f0a93db0220d8e9a85c.jpg",
    "type" : "image/jpeg",
    "bitrate" : 0,
    "duration" : 0,
    "title" : null,
    "properties" : null,
    "alternate" : [ {
      "href" : "https://i221.ntcdntempv3.com/data/images/39619/931927/051-2058ac5.jpg?data=net",
      "type" : "image/jpeg",
      "bitrate" : 0,
      "duration" : 0,
      "title" : null,
      "properties" : null,
      "alternate" : null
    } ]
  }, {
    "href" : "https://raw.githubusercontent.com/quetcccd/comic_storage9/main/IMAGE/IMAGE_2ed46c0b408d7a8e54681c8ec9c6d249_40ba63ee960f580caa0f940d0903dd92_4d72a171f5084ba2819f58103ca6c00f.jpg",
    "type" : "image/jpeg",
    "bitrate" : 0,
    "duration" : 0,
    "title" : null,
    "properties" : null,
    "alternate" : [ {
      "href" : "https://i221.ntcdntempv3.com/data/images/39619/931927/052-c6838a1.jpg?data=net",
      "type" : "image/jpeg",
      "bitrate" : 0,
      "duration" : 0,
      "title" : null,
      "properties" : null,
      "alternate" : null
    } ]
  }, {
    "href" : "https://raw.githubusercontent.com/quetcccd/comic_storage9/main/IMAGE/IMAGE_2ed46c0b408d7a8e54681c8ec9c6d249_40ba63ee960f580caa0f940d0903dd92_b0ce72da8bc8fbe37f8bb687193bc670.jpg",
    "type" : "image/jpeg",
    "bitrate" : 0,
    "duration" : 0,
    "title" : null,
    "properties" : null,
    "alternate" : [ {
      "href" : "https://i221.ntcdntempv3.com/data/images/39619/931927/053-de2547b.jpg?data=net",
      "type" : "image/jpeg",
      "bitrate" : 0,
      "duration" : 0,
      "title" : null,
      "properties" : null,
      "alternate" : null
    } ]
  }, {
    "href" : "https://raw.githubusercontent.com/quetcccd/comic_storage9/main/IMAGE/IMAGE_2ed46c0b408d7a8e54681c8ec9c6d249_40ba63ee960f580caa0f940d0903dd92_298348874dbc27a6f315cd8dedd0b30a.jpg",
    "type" : "image/jpeg",
    "bitrate" : 0,
    "duration" : 0,
    "title" : null,
    "properties" : null,
    "alternate" : [ {
      "href" : "https://i221.ntcdntempv3.com/data/images/39619/931927/054-5b591ad.jpg?data=net",
      "type" : "image/jpeg",
      "bitrate" : 0,
      "duration" : 0,
      "title" : null,
      "properties" : null,
      "alternate" : null
    } ]
  }, {
    "href" : "https://raw.githubusercontent.com/quetcccd/comic_storage9/main/IMAGE/IMAGE_2ed46c0b408d7a8e54681c8ec9c6d249_40ba63ee960f580caa0f940d0903dd92_b5ece952a1bb5da5a2e49c764609ba6e.jpg",
    "type" : "image/jpeg",
    "bitrate" : 0,
    "duration" : 0,
    "title" : null,
    "properties" : null,
    "alternate" : [ {
      "href" : "https://i221.ntcdntempv3.com/data/images/39619/931927/055-af66f08.jpg?data=net",
      "type" : "image/jpeg",
      "bitrate" : 0,
      "duration" : 0,
      "title" : null,
      "properties" : null,
      "alternate" : null
    } ]
  }, {
    "href" : "https://raw.githubusercontent.com/quetcccd/comic_storage9/main/IMAGE/IMAGE_2ed46c0b408d7a8e54681c8ec9c6d249_40ba63ee960f580caa0f940d0903dd92_76ae4ec2968278faf1596c06b895b9aa.jpg",
    "type" : "image/jpeg",
    "bitrate" : 0,
    "duration" : 0,
    "title" : null,
    "properties" : null,
    "alternate" : [ {
      "href" : "https://i221.ntcdntempv3.com/data/images/39619/931927/056-4c6fe8a.jpg?data=net",
      "type" : "image/jpeg",
      "bitrate" : 0,
      "duration" : 0,
      "title" : null,
      "properties" : null,
      "alternate" : null
    } ]
  }, {
    "href" : "https://raw.githubusercontent.com/quetcccd/comic_storage9/main/IMAGE/IMAGE_2ed46c0b408d7a8e54681c8ec9c6d249_40ba63ee960f580caa0f940d0903dd92_996cd0a042b3d1cda9e4ea7ad75ad60a.jpg",
    "type" : "image/jpeg",
    "bitrate" : 0,
    "duration" : 0,
    "title" : null,
    "properties" : null,
    "alternate" : [ {
      "href" : "https://i221.ntcdntempv3.com/data/images/39619/931927/057-7dba4ae.jpg?data=net",
      "type" : "image/jpeg",
      "bitrate" : 0,
      "duration" : 0,
      "title" : null,
      "properties" : null,
      "alternate" : null
    } ]
  }, {
    "href" : "https://raw.githubusercontent.com/quetcccd/comic_storage9/main/IMAGE/IMAGE_2ed46c0b408d7a8e54681c8ec9c6d249_40ba63ee960f580caa0f940d0903dd92_6da2f06c36cf69b0dfdf1493d4921273.jpg",
    "type" : "image/jpeg",
    "bitrate" : 0,
    "duration" : 0,
    "title" : null,
    "properties" : null,
    "alternate" : [ {
      "href" : "https://i221.ntcdntempv3.com/data/images/39619/931927/058-cbde678.jpg?data=net",
      "type" : "image/jpeg",
      "bitrate" : 0,
      "duration" : 0,
      "title" : null,
      "properties" : null,
      "alternate" : null
    } ]
  }, {
    "href" : "https://raw.githubusercontent.com/quetcccd/comic_storage9/main/IMAGE/IMAGE_2ed46c0b408d7a8e54681c8ec9c6d249_40ba63ee960f580caa0f940d0903dd92_e4307385ea390a7093687bfc4cfd5f4b.jpg",
    "type" : "image/jpeg",
    "bitrate" : 0,
    "duration" : 0,
    "title" : null,
    "properties" : null,
    "alternate" : [ {
      "href" : "https://i221.ntcdntempv3.com/data/images/39619/931927/059-1677f57.jpg?data=net",
      "type" : "image/jpeg",
      "bitrate" : 0,
      "duration" : 0,
      "title" : null,
      "properties" : null,
      "alternate" : null
    } ]
  }, {
    "href" : "https://raw.githubusercontent.com/quetcccd/comic_storage9/main/IMAGE/IMAGE_2ed46c0b408d7a8e54681c8ec9c6d249_40ba63ee960f580caa0f940d0903dd92_77c1ef15ef18bdfd218e82642681150b.jpg",
    "type" : "image/jpeg",
    "bitrate" : 0,
    "duration" : 0,
    "title" : null,
    "properties" : null,
    "alternate" : [ {
      "href" : "https://i221.ntcdntempv3.com/data/images/39619/931927/060-ead395f.jpg?data=net",
      "type" : "image/jpeg",
      "bitrate" : 0,
      "duration" : 0,
      "title" : null,
      "properties" : null,
      "alternate" : null
    } ]
  }, {
    "href" : "https://raw.githubusercontent.com/quetcccd/comic_storage9/main/IMAGE/IMAGE_2ed46c0b408d7a8e54681c8ec9c6d249_40ba63ee960f580caa0f940d0903dd92_3fb27cd8c70a9d322b19fbde853a4d5c.jpg",
    "type" : "image/jpeg",
    "bitrate" : 0,
    "duration" : 0,
    "title" : null,
    "properties" : null,
    "alternate" : [ {
      "href" : "https://i221.ntcdntempv3.com/data/images/39619/931927/061-224e45e.jpg?data=net",
      "type" : "image/jpeg",
      "bitrate" : 0,
      "duration" : 0,
      "title" : null,
      "properties" : null,
      "alternate" : null
    } ]
  }, {
    "href" : "https://raw.githubusercontent.com/quetcccd/comic_storage9/main/IMAGE/IMAGE_2ed46c0b408d7a8e54681c8ec9c6d249_40ba63ee960f580caa0f940d0903dd92_3038681554901c92e86f61c30b61eca2.jpg",
    "type" : "image/jpeg",
    "bitrate" : 0,
    "duration" : 0,
    "title" : null,
    "properties" : null,
    "alternate" : [ {
      "href" : "https://i221.ntcdntempv3.com/data/images/39619/931927/062-32b4bd9.jpg?data=net",
      "type" : "image/jpeg",
      "bitrate" : 0,
      "duration" : 0,
      "title" : null,
      "properties" : null,
      "alternate" : null
    } ]
  }, {
    "href" : "https://raw.githubusercontent.com/quetcccd/comic_storage9/main/IMAGE/IMAGE_2ed46c0b408d7a8e54681c8ec9c6d249_40ba63ee960f580caa0f940d0903dd92_ea5c7ae2476073cd139b321617810749.jpg",
    "type" : "image/jpeg",
    "bitrate" : 0,
    "duration" : 0,
    "title" : null,
    "properties" : null,
    "alternate" : [ {
      "href" : "https://i221.ntcdntempv3.com/data/images/39619/931927/063-0d369e5.jpg?data=net",
      "type" : "image/jpeg",
      "bitrate" : 0,
      "duration" : 0,
      "title" : null,
      "properties" : null,
      "alternate" : null
    } ]
  }, {
    "href" : "https://raw.githubusercontent.com/quetcccd/comic_storage9/main/IMAGE/IMAGE_2ed46c0b408d7a8e54681c8ec9c6d249_40ba63ee960f580caa0f940d0903dd92_6857e4df4de8cceda0c9416b86c91e40.jpg",
    "type" : "image/jpeg",
    "bitrate" : 0,
    "duration" : 0,
    "title" : null,
    "properties" : null,
    "alternate" : [ {
      "href" : "https://i221.ntcdntempv3.com/data/images/39619/931927/064-a2e30d9.jpg?data=net",
      "type" : "image/jpeg",
      "bitrate" : 0,
      "duration" : 0,
      "title" : null,
      "properties" : null,
      "alternate" : null
    } ]
  }, {
    "href" : "https://raw.githubusercontent.com/quetcccd/comic_storage9/main/IMAGE/IMAGE_2ed46c0b408d7a8e54681c8ec9c6d249_40ba63ee960f580caa0f940d0903dd92_a2d768de5c1852f9e55b9b5822afad9b.jpg",
    "type" : "image/jpeg",
    "bitrate" : 0,
    "duration" : 0,
    "title" : null,
    "properties" : null,
    "alternate" : [ {
      "href" : "https://i221.ntcdntempv3.com/data/images/39619/931927/065-d54d6fc.jpg?data=net",
      "type" : "image/jpeg",
      "bitrate" : 0,
      "duration" : 0,
      "title" : null,
      "properties" : null,
      "alternate" : null
    } ]
  }, {
    "href" : "https://raw.githubusercontent.com/quetcccd/comic_storage9/main/IMAGE/IMAGE_2ed46c0b408d7a8e54681c8ec9c6d249_40ba63ee960f580caa0f940d0903dd92_591ed3ba0c2b4e634c5816770bbcbccd.jpg",
    "type" : "image/jpeg",
    "bitrate" : 0,
    "duration" : 0,
    "title" : null,
    "properties" : null,
    "alternate" : [ {
      "href" : "https://i221.ntcdntempv3.com/data/images/39619/931927/066-3f334ee.jpg?data=net",
      "type" : "image/jpeg",
      "bitrate" : 0,
      "duration" : 0,
      "title" : null,
      "properties" : null,
      "alternate" : null
    } ]
  }, {
    "href" : "https://raw.githubusercontent.com/quetcccd/comic_storage9/main/IMAGE/IMAGE_2ed46c0b408d7a8e54681c8ec9c6d249_40ba63ee960f580caa0f940d0903dd92_0911854344ad3b3f8db2bcd551d8bdbe.jpg",
    "type" : "image/jpeg",
    "bitrate" : 0,
    "duration" : 0,
    "title" : null,
    "properties" : null,
    "alternate" : [ {
      "href" : "https://i221.ntcdntempv3.com/data/images/39619/931927/067-9bb6093.jpg?data=net",
      "type" : "image/jpeg",
      "bitrate" : 0,
      "duration" : 0,
      "title" : null,
      "properties" : null,
      "alternate" : null
    } ]
  }, {
    "href" : "https://raw.githubusercontent.com/quetcccd/comic_storage9/main/IMAGE/IMAGE_2ed46c0b408d7a8e54681c8ec9c6d249_40ba63ee960f580caa0f940d0903dd92_25fd4e6259a6689fe5105b3f17737ee7.jpg",
    "type" : "image/jpeg",
    "bitrate" : 0,
    "duration" : 0,
    "title" : null,
    "properties" : null,
    "alternate" : [ {
      "href" : "https://i221.ntcdntempv3.com/data/images/39619/931927/068-48a0abb.jpg?data=net",
      "type" : "image/jpeg",
      "bitrate" : 0,
      "duration" : 0,
      "title" : null,
      "properties" : null,
      "alternate" : null
    } ]
  }, {
    "href" : "https://raw.githubusercontent.com/quetcccd/comic_storage9/main/IMAGE/IMAGE_2ed46c0b408d7a8e54681c8ec9c6d249_40ba63ee960f580caa0f940d0903dd92_d81d847b6b60de472bc66ee5884128ee.jpg",
    "type" : "image/jpeg",
    "bitrate" : 0,
    "duration" : 0,
    "title" : null,
    "properties" : null,
    "alternate" : [ {
      "href" : "https://i221.ntcdntempv3.com/data/images/39619/931927/069-6b585b9.jpg?data=net",
      "type" : "image/jpeg",
      "bitrate" : 0,
      "duration" : 0,
      "title" : null,
      "properties" : null,
      "alternate" : null
    } ]
  }, {
    "href" : "https://raw.githubusercontent.com/quetcccd/comic_storage9/main/IMAGE/IMAGE_2ed46c0b408d7a8e54681c8ec9c6d249_40ba63ee960f580caa0f940d0903dd92_4cbeb8f924c75c04db9972025bc9aadd.jpg",
    "type" : "image/jpeg",
    "bitrate" : 0,
    "duration" : 0,
    "title" : null,
    "properties" : null,
    "alternate" : [ {
      "href" : "https://i221.ntcdntempv3.com/data/images/39619/931927/070-565cfce.jpg?data=net",
      "type" : "image/jpeg",
      "bitrate" : 0,
      "duration" : 0,
      "title" : null,
      "properties" : null,
      "alternate" : null
    } ]
  }, {
    "href" : "https://raw.githubusercontent.com/quetcccd/comic_storage9/main/IMAGE/IMAGE_2ed46c0b408d7a8e54681c8ec9c6d249_40ba63ee960f580caa0f940d0903dd92_7a176eee0355e0a38ba0f53f3e053f5d.jpg",
    "type" : "image/jpeg",
    "bitrate" : 0,
    "duration" : 0,
    "title" : null,
    "properties" : null,
    "alternate" : [ {
      "href" : "https://i221.ntcdntempv3.com/data/images/39619/931927/071-7c13a6f.jpg?data=net",
      "type" : "image/jpeg",
      "bitrate" : 0,
      "duration" : 0,
      "title" : null,
      "properties" : null,
      "alternate" : null
    } ]
  }, {
    "href" : "https://raw.githubusercontent.com/quetcccd/comic_storage9/main/IMAGE/IMAGE_2ed46c0b408d7a8e54681c8ec9c6d249_40ba63ee960f580caa0f940d0903dd92_7dc00784665a4b06c763fe393781f0d2.jpg",
    "type" : "image/jpeg",
    "bitrate" : 0,
    "duration" : 0,
    "title" : null,
    "properties" : null,
    "alternate" : [ {
      "href" : "https://i221.ntcdntempv3.com/data/images/39619/931927/072-90af1bc.jpg?data=net",
      "type" : "image/jpeg",
      "bitrate" : 0,
      "duration" : 0,
      "title" : null,
      "properties" : null,
      "alternate" : null
    } ]
  }, {
    "href" : "https://raw.githubusercontent.com/quetcccd/comic_storage9/main/IMAGE/IMAGE_2ed46c0b408d7a8e54681c8ec9c6d249_40ba63ee960f580caa0f940d0903dd92_f3566fc013ab3185420d0de02e30d17f.jpg",
    "type" : "image/jpeg",
    "bitrate" : 0,
    "duration" : 0,
    "title" : null,
    "properties" : null,
    "alternate" : [ {
      "href" : "https://i221.ntcdntempv3.com/data/images/39619/931927/073-2f499b5.jpg?data=net",
      "type" : "image/jpeg",
      "bitrate" : 0,
      "duration" : 0,
      "title" : null,
      "properties" : null,
      "alternate" : null
    } ]
  }, {
    "href" : "https://raw.githubusercontent.com/quetcccd/comic_storage9/main/IMAGE/IMAGE_2ed46c0b408d7a8e54681c8ec9c6d249_40ba63ee960f580caa0f940d0903dd92_2a0a81cda2e2c6a16a3d9c594ecd483e.jpg",
    "type" : "image/jpeg",
    "bitrate" : 0,
    "duration" : 0,
    "title" : null,
    "properties" : null,
    "alternate" : [ {
      "href" : "https://i221.ntcdntempv3.com/data/images/39619/931927/074-61da641.jpg?data=net",
      "type" : "image/jpeg",
      "bitrate" : 0,
      "duration" : 0,
      "title" : null,
      "properties" : null,
      "alternate" : null
    } ]
  }, {
    "href" : "https://raw.githubusercontent.com/quetcccd/comic_storage9/main/IMAGE/IMAGE_2ed46c0b408d7a8e54681c8ec9c6d249_40ba63ee960f580caa0f940d0903dd92_2b3761daf8b5fb604be9912eb7373a10.jpg",
    "type" : "image/jpeg",
    "bitrate" : 0,
    "duration" : 0,
    "title" : null,
    "properties" : null,
    "alternate" : [ {
      "href" : "https://i221.ntcdntempv3.com/data/images/39619/931927/075-a538182.jpg?data=net",
      "type" : "image/jpeg",
      "bitrate" : 0,
      "duration" : 0,
      "title" : null,
      "properties" : null,
      "alternate" : null
    } ]
  }, {
    "href" : "https://raw.githubusercontent.com/quetcccd/comic_storage9/main/IMAGE/IMAGE_2ed46c0b408d7a8e54681c8ec9c6d249_40ba63ee960f580caa0f940d0903dd92_df4cf113c8899dacbe066bd689976685.jpg",
    "type" : "image/jpeg",
    "bitrate" : 0,
    "duration" : 0,
    "title" : null,
    "properties" : null,
    "alternate" : [ {
      "href" : "https://i221.ntcdntempv3.com/data/images/39619/931927/076-7ba65fd.jpg?data=net",
      "type" : "image/jpeg",
      "bitrate" : 0,
      "duration" : 0,
      "title" : null,
      "properties" : null,
      "alternate" : null
    } ]
  }, {
    "href" : "https://raw.githubusercontent.com/quetcccd/comic_storage9/main/IMAGE/IMAGE_2ed46c0b408d7a8e54681c8ec9c6d249_40ba63ee960f580caa0f940d0903dd92_71720cc7aae47256bdd50c303e4c8fc7.jpg",
    "type" : "image/jpeg",
    "bitrate" : 0,
    "duration" : 0,
    "title" : null,
    "properties" : null,
    "alternate" : [ {
      "href" : "https://i221.ntcdntempv3.com/data/images/39619/931927/077-3013e61.jpg?data=net",
      "type" : "image/jpeg",
      "bitrate" : 0,
      "duration" : 0,
      "title" : null,
      "properties" : null,
      "alternate" : null
    } ]
  }, {
    "href" : "https://raw.githubusercontent.com/quetcccd/comic_storage9/main/IMAGE/IMAGE_2ed46c0b408d7a8e54681c8ec9c6d249_40ba63ee960f580caa0f940d0903dd92_0339cdfb126a6c06b1e1fb4444d988a4.jpg",
    "type" : "image/jpeg",
    "bitrate" : 0,
    "duration" : 0,
    "title" : null,
    "properties" : null,
    "alternate" : [ {
      "href" : "https://i221.ntcdntempv3.com/data/images/39619/931927/078-f64fb7b.jpg?data=net",
      "type" : "image/jpeg",
      "bitrate" : 0,
      "duration" : 0,
      "title" : null,
      "properties" : null,
      "alternate" : null
    } ]
  }, {
    "href" : "https://raw.githubusercontent.com/quetcccd/comic_storage9/main/IMAGE/IMAGE_2ed46c0b408d7a8e54681c8ec9c6d249_40ba63ee960f580caa0f940d0903dd92_cd616bc1f13df029d6748e42a3d03d0e.jpg",
    "type" : "image/jpeg",
    "bitrate" : 0,
    "duration" : 0,
    "title" : null,
    "properties" : null,
    "alternate" : [ {
      "href" : "https://i221.ntcdntempv3.com/data/images/39619/931927/079-9cd7528.jpg?data=net",
      "type" : "image/jpeg",
      "bitrate" : 0,
      "duration" : 0,
      "title" : null,
      "properties" : null,
      "alternate" : null
    } ]
  }, {
    "href" : "https://raw.githubusercontent.com/quetcccd/comic_storage9/main/IMAGE/IMAGE_2ed46c0b408d7a8e54681c8ec9c6d249_40ba63ee960f580caa0f940d0903dd92_a8b165d7a3b2ef00c834689c2a7afa17.jpg",
    "type" : "image/jpeg",
    "bitrate" : 0,
    "duration" : 0,
    "title" : null,
    "properties" : null,
    "alternate" : [ {
      "href" : "https://i221.ntcdntempv3.com/data/images/39619/931927/080-c4512e4.jpg?data=net",
      "type" : "image/jpeg",
      "bitrate" : 0,
      "duration" : 0,
      "title" : null,
      "properties" : null,
      "alternate" : null
    } ]
  }, {
    "href" : "https://raw.githubusercontent.com/quetcccd/comic_storage9/main/IMAGE/IMAGE_2ed46c0b408d7a8e54681c8ec9c6d249_40ba63ee960f580caa0f940d0903dd92_2c9e75c5b0513b863f15df059547af75.jpg",
    "type" : "image/jpeg",
    "bitrate" : 0,
    "duration" : 0,
    "title" : null,
    "properties" : null,
    "alternate" : [ {
      "href" : "https://i221.ntcdntempv3.com/data/images/39619/931927/081-5952f90.jpg?data=net",
      "type" : "image/jpeg",
      "bitrate" : 0,
      "duration" : 0,
      "title" : null,
      "properties" : null,
      "alternate" : null
    } ]
  }, {
    "href" : "https://raw.githubusercontent.com/quetcccd/comic_storage9/main/IMAGE/IMAGE_2ed46c0b408d7a8e54681c8ec9c6d249_40ba63ee960f580caa0f940d0903dd92_be99e44df684ec1651e78c38adf53332.jpg",
    "type" : "image/jpeg",
    "bitrate" : 0,
    "duration" : 0,
    "title" : null,
    "properties" : null,
    "alternate" : [ {
      "href" : "https://i221.ntcdntempv3.com/data/images/39619/931927/082-b49a687.jpg?data=net",
      "type" : "image/jpeg",
      "bitrate" : 0,
      "duration" : 0,
      "title" : null,
      "properties" : null,
      "alternate" : null
    } ]
  }, {
    "href" : "https://raw.githubusercontent.com/quetcccd/comic_storage9/main/IMAGE/IMAGE_2ed46c0b408d7a8e54681c8ec9c6d249_40ba63ee960f580caa0f940d0903dd92_e782f991e4e1b3075051db79c9da3fc6.jpg",
    "type" : "image/jpeg",
    "bitrate" : 0,
    "duration" : 0,
    "title" : null,
    "properties" : null,
    "alternate" : [ {
      "href" : "https://i221.ntcdntempv3.com/data/images/39619/931927/083-d02b457.jpg?data=net",
      "type" : "image/jpeg",
      "bitrate" : 0,
      "duration" : 0,
      "title" : null,
      "properties" : null,
      "alternate" : null
    } ]
  }, {
    "href" : "https://raw.githubusercontent.com/quetcccd/comic_storage9/main/IMAGE/IMAGE_2ed46c0b408d7a8e54681c8ec9c6d249_40ba63ee960f580caa0f940d0903dd92_3280644b277e975386ea1198eba1d2dc.jpg",
    "type" : "image/jpeg",
    "bitrate" : 0,
    "duration" : 0,
    "title" : null,
    "properties" : null,
    "alternate" : [ {
      "href" : "https://i221.ntcdntempv3.com/data/images/39619/931927/084-990a2c3.jpg?data=net",
      "type" : "image/jpeg",
      "bitrate" : 0,
      "duration" : 0,
      "title" : null,
      "properties" : null,
      "alternate" : null
    } ]
  }, {
    "href" : "https://raw.githubusercontent.com/quetcccd/comic_storage9/main/IMAGE/IMAGE_2ed46c0b408d7a8e54681c8ec9c6d249_40ba63ee960f580caa0f940d0903dd92_c6782787a03f24042baca47b0438cab6.jpg",
    "type" : "image/jpeg",
    "bitrate" : 0,
    "duration" : 0,
    "title" : null,
    "properties" : null,
    "alternate" : [ {
      "href" : "https://i221.ntcdntempv3.com/data/images/39619/931927/085-c5e07c8.jpg?data=net",
      "type" : "image/jpeg",
      "bitrate" : 0,
      "duration" : 0,
      "title" : null,
      "properties" : null,
      "alternate" : null
    } ]
  }, {
    "href" : "https://raw.githubusercontent.com/quetcccd/comic_storage9/main/IMAGE/IMAGE_2ed46c0b408d7a8e54681c8ec9c6d249_40ba63ee960f580caa0f940d0903dd92_00b51d151e8e670d1e01ec0f0e2065a5.jpg",
    "type" : "image/jpeg",
    "bitrate" : 0,
    "duration" : 0,
    "title" : null,
    "properties" : null,
    "alternate" : [ {
      "href" : "https://i221.ntcdntempv3.com/data/images/39619/931927/086-a0be87e.jpg?data=net",
      "type" : "image/jpeg",
      "bitrate" : 0,
      "duration" : 0,
      "title" : null,
      "properties" : null,
      "alternate" : null
    } ]
  }, {
    "href" : "https://raw.githubusercontent.com/quetcccd/comic_storage9/main/IMAGE/IMAGE_2ed46c0b408d7a8e54681c8ec9c6d249_40ba63ee960f580caa0f940d0903dd92_410ca8462490bb1f3b1d3c779aebea15.jpg",
    "type" : "image/jpeg",
    "bitrate" : 0,
    "duration" : 0,
    "title" : null,
    "properties" : null,
    "alternate" : [ {
      "href" : "https://i221.ntcdntempv3.com/data/images/39619/931927/087-fb51c7b.jpg?data=net",
      "type" : "image/jpeg",
      "bitrate" : 0,
      "duration" : 0,
      "title" : null,
      "properties" : null,
      "alternate" : null
    } ]
  }, {
    "href" : "https://raw.githubusercontent.com/quetcccd/comic_storage9/main/IMAGE/IMAGE_2ed46c0b408d7a8e54681c8ec9c6d249_40ba63ee960f580caa0f940d0903dd92_2eb12e2d30fc7496ca99faea3d8eb630.jpg",
    "type" : "image/jpeg",
    "bitrate" : 0,
    "duration" : 0,
    "title" : null,
    "properties" : null,
    "alternate" : [ {
      "href" : "https://i221.ntcdntempv3.com/data/images/39619/931927/088-d84eb39.jpg?data=net",
      "type" : "image/jpeg",
      "bitrate" : 0,
      "duration" : 0,
      "title" : null,
      "properties" : null,
      "alternate" : null
    } ]
  } ],
  "toc" : null,
  "@context" : "https://readium.org/webpub-manifest/context.jsonld"
}